README.txt
setup.py
NoelOCR/__init__.py
NoelOCR.egg-info/PKG-INFO
NoelOCR.egg-info/SOURCES.txt
NoelOCR.egg-info/dependency_links.txt
NoelOCR.egg-info/requires.txt
NoelOCR.egg-info/top_level.txt