Metadata-Version: 1.1
Name: NoelOCR
Version: 0.0.8
Summary: Python Optical Character Recognition based libray for text extraction of scanned PDF
Home-page: UNKNOWN
Author: Noel Moses Mwadende
Author-email: mosesnoel02@gmail.com
License: MIT
Keywords: Opctical Character Recognition,Scanned PDF,PDF Text Extraction,OCR
Platform: UNKNOWN
Classifier: Development Status :: 3 - Alpha
Classifier: Intended Audience :: Developers
Classifier: Operating System :: POSIX :: Linux
Classifier: License :: OSI Approved :: MIT License
Classifier: Programming Language :: Python :: 3
